haruna/__init__.py
haruna/agents/__init__.py
haruna/agents/agent.py
haruna/agents/categorical_dqn.py
haruna/agents/double_dqn.py
haruna/agents/dueling_dqn.py
haruna/agents/noisy_dqn.py
haruna/agents/td3.py
haruna/base/__init__.py
haruna/base/account.py
haruna/base/balance.py
haruna/base/enum.py
haruna/base/exchange.py
haruna/base/market.py
haruna/base/order.py
haruna/common/__init__.py
haruna/common/evaluation.py
haruna/common/replay_buffer.py
haruna/common/schedules.py
haruna/common/segment_tree.py
haruna/common/utils.py
haruna/envs/__init__.py
haruna/envs/market_making.py
haruna/envs/test_tradingenv.py
haruna/envs/trading.py
haruna/envs/utils.py
haruna/nn/__init__.py
haruna/nn/dueling.py
haruna/nn/fcn.py
haruna/nn/noisy_linear.py
haruna/nn/test_fcn.py
haruna/optim/__init__.py
haruna/optim/radam.py
haruna/optim/rmsprop.py
haruna/transforms/__init__.py
haruna/transforms/segmentation.py
haruna/utils/__init__.py
haruna/utils/test_timeit.py
haruna/utils/timeit.py
haruna/utils/utils.py
haruna-0.2.0.dist-info/LICENSE
haruna-0.2.0.dist-info/METADATA
haruna-0.2.0.dist-info/WHEEL
haruna-0.2.0.dist-info/RECORD
