Metadata-Version: 2.1
Name: haruna
Version: 0.2.0
Summary: 
Author: なるみ
Author-email: 4680567+narumiruna@users.noreply.github.com
Requires-Python: >=3.9,<4.0
Classifier: Programming Language :: Python :: 3
Classifier: Programming Language :: Python :: 3.9
Classifier: Programming Language :: Python :: 3.10
Classifier: Programming Language :: Python :: 3.11
Requires-Dist: cryptodataset (>=0.3.9,<0.4.0)
Requires-Dist: gymnasium (>=0.28.0,<0.29.0)
Requires-Dist: loguru (>=0.6.0,<0.7.0)
Requires-Dist: mlflow (>=2.2.2,<3.0.0)
Requires-Dist: numba (>=0.56.4,<0.57.0)
Requires-Dist: numpy (>=1.22.4,<2.0.0)
Requires-Dist: pandas-ta (>=0.3.14b0,<0.4.0)
Requires-Dist: pyyaml (>=6.0,<7.0)
Requires-Dist: quantstats (>=0.0.59,<0.0.60)
Requires-Dist: torch (>=1.13.1,<2.0.0)
Requires-Dist: torchmetrics (>=0.11.4,<0.12.0)
Requires-Dist: torchvision (>=0.14.1,<0.15.0)
Requires-Dist: tqdm (>=4.65.0,<5.0.0)
